ssh_server_audit-1.0.2.data/data/local/etc/ssh-server-audit/config.yml
sshserveraudit/__init__.py
sshserveraudit/exception.py
sshserveraudit/controller/__init__.py
sshserveraudit/controller/abstract.py
sshserveraudit/controller/authenticity.py
sshserveraudit/controller/healthcheck.py
sshserveraudit/controller/http.py
sshserveraudit/entity/__init__.py
sshserveraudit/entity/host.py
sshserveraudit/factory/node.py
sshserveraudit/factory/notifier.py
sshserveraudit/service/notify.py
sshserveraudit/service/ssh.py
sshserveraudit/validator/__init__.py
sshserveraudit/validator/health.py
sshserveraudit/validator/hostauthenticity.py
sshserveraudit/valueobject/__init__.py
sshserveraudit/valueobject/validator.py
ssh_server_audit-1.0.2.dist-info/AUTHORS
ssh_server_audit-1.0.2.dist-info/METADATA
ssh_server_audit-1.0.2.dist-info/WHEEL
ssh_server_audit-1.0.2.dist-info/entry_points.txt
ssh_server_audit-1.0.2.dist-info/pbr.json
ssh_server_audit-1.0.2.dist-info/top_level.txt
ssh_server_audit-1.0.2.dist-info/RECORD
