Metadata-Version: 2.1
Name: ssh-server-audit
Version: 1.0.2
Summary: Performs validation of remote filesystem integrity and executes health checks. Supports self-repair commands
Home-page: https://github.com/Wolnosciowiec/ssh-server-audit
Author: Marek Andrzejczak
Author-email: marek_andrzejczak@riseup.net
License: LGPLv3
Platform: UNKNOWN
Classifier: Development Status :: 5 - Production/Stable
Classifier: Environment :: Web Environment
Classifier: Intended Audience :: Developers
Classifier: Intended Audience :: System Administrators
Classifier: License :: OSI Approved :: GNU General Public License v3 or later (GPLv3+)
Classifier: Natural Language :: English
Classifier: Operating System :: POSIX :: Linux
Classifier: Programming Language :: Python :: 3 :: Only
Classifier: Topic :: Utilities
Classifier: Topic :: Software Development :: Version Control
Classifier: Topic :: System :: Systems Administration
Requires-Python: >=3.5
Requires-Dist: tornado (>=4.5)
Requires-Dist: paramiko (>=2.4)
Requires-Dist: PyYAML (>=3.12)
Requires-Dist: PySocks (>=1.6)
Requires-Dist: pbr (>=5.1)
Requires-Dist: setuptools (>=40.4.3)
Requires-Dist: requests
Requires-Dist: requests[socks]
Requires-Dist: unittest-data-provider
Requires-Dist: coverage
Requires-Dist: mock
